aark_sdk/__init__.py
aark_sdk/client.py
aark_sdk/abis/ContractReader.json
aark_sdk/abis/OctRouter.json
aark_sdk-0.1.9.dist-info/LICENSE.txt
aark_sdk-0.1.9.dist-info/METADATA
aark_sdk-0.1.9.dist-info/WHEEL
aark_sdk-0.1.9.dist-info/top_level.txt
aark_sdk-0.1.9.dist-info/RECORD
