Metadata-Version: 2.1
Name: aark-sdk
Version: 0.1.9
Home-page: https://github.com/Aark-Digital/python-aark-sdk
Author: 
Author-email: 
Classifier: Development Status :: 2 - Pre-Alpha
Classifier: Environment :: MacOS X
Classifier: Programming Language :: Python :: 3.9
License-File: LICENSE.txt
Requires-Dist: aiohttp ==3.8.6
Requires-Dist: aiosignal ==1.3.1
Requires-Dist: async-timeout ==4.0.3
Requires-Dist: attrs ==23.1.0
Requires-Dist: bitarray ==2.8.2
Requires-Dist: certifi ==2023.7.22
Requires-Dist: charset-normalizer ==3.3.2
Requires-Dist: cytoolz ==0.12.2
Requires-Dist: eth-abi ==4.2.1
Requires-Dist: eth-account ==0.10.0
Requires-Dist: eth-hash ==0.5.2
Requires-Dist: eth-keyfile ==0.6.1
Requires-Dist: eth-keys ==0.4.0
Requires-Dist: eth-rlp ==0.3.0
Requires-Dist: eth-typing ==3.5.1
Requires-Dist: eth-utils ==2.3.0
Requires-Dist: frozenlist ==1.4.0
Requires-Dist: hexbytes ==0.3.1
Requires-Dist: idna ==3.4
Requires-Dist: jsonschema ==4.19.2
Requires-Dist: jsonschema-specifications ==2023.7.1
Requires-Dist: lru-dict ==1.2.0
Requires-Dist: multidict ==6.0.4
Requires-Dist: parsimonious ==0.9.0
Requires-Dist: protobuf ==4.25.0
Requires-Dist: pycryptodome ==3.19.0
Requires-Dist: pyunormalize ==15.0.0
Requires-Dist: referencing ==0.30.2
Requires-Dist: regex ==2023.10.3
Requires-Dist: requests ==2.31.0
Requires-Dist: rlp ==3.0.0
Requires-Dist: rpds-py ==0.10.6
Requires-Dist: toolz ==0.12.0
Requires-Dist: typing-extensions ==4.8.0
Requires-Dist: urllib3 ==2.0.7
Requires-Dist: web3 ==6.11.2
Requires-Dist: websockets ==12.0
Requires-Dist: yarl ==1.9.2
